sk_calculator/__init__.py
sk_calculator/calculatortest_.py
sk_calculator/validationtest_.py
sk_calculator/controller/__init__.py
sk_calculator/controller/base.py
sk_calculator/controller/bracket.py
sk_calculator/controller/default.py
sk_calculator/controller/error.py
sk_calculator/controller/function.py
sk_calculator/controller/process.py
sk_calculator/controller/recorder.py
sk_calculator/controller/validation.py
sk_calculator/function/__init__.py
sk_calculator/function/abs.py
sk_calculator/function/default.py
sk_calculator/function/exp.py
sk_calculator/function/ln.py
sk_calculator/function/log.py
sk_calculator/function/sqrt.py
sk_calculator/function/custom_function/__init__.py
sk_calculator/function/custom_function/custom_function.py
sk_calculator/function/trigonometric_function/__init__.py
sk_calculator/function/trigonometric_function/cos.py
sk_calculator/function/trigonometric_function/cosec.py
sk_calculator/function/trigonometric_function/cot.py
sk_calculator/function/trigonometric_function/sec.py
sk_calculator/function/trigonometric_function/sin.py
sk_calculator/function/trigonometric_function/tan.py
sk_calculator/function/trigonometric_inverse_function/__init__.py
sk_calculator/function/trigonometric_inverse_function/acos.py
sk_calculator/function/trigonometric_inverse_function/acosec.py
sk_calculator/function/trigonometric_inverse_function/acot.py
sk_calculator/function/trigonometric_inverse_function/asec.py
sk_calculator/function/trigonometric_inverse_function/asin.py
sk_calculator/function/trigonometric_inverse_function/atan.py
sk_calculator/operations/__init__.py
sk_calculator/operations/addition.py
sk_calculator/operations/bracket.py
sk_calculator/operations/division.py
sk_calculator/operations/mod.py
sk_calculator/operations/multiplication.py
sk_calculator/operations/power.py
sk_calculator/operations/substraction.py
sk_calculator/operations/unary.py
sk_calculator/process/__init__.py
sk_calculator/process/default.py
sk_calculator/process/e.py
sk_calculator-1.0.101.dist-info/LICENSE.txt
sk_calculator-1.0.101.dist-info/METADATA
sk_calculator-1.0.101.dist-info/WHEEL
sk_calculator-1.0.101.dist-info/top_level.txt
sk_calculator-1.0.101.dist-info/RECORD
