Metadata-Version: 2.1
Name: sk-calculator
Version: 1.0.101
Summary: A simple calculator program
Author: gkibria
Author-email: gkibria121@gmail.com
Keywords: python,calculator,python calculator,gk calculator,advanced calculator
Classifier: Programming Language :: Python :: 3
Classifier: License :: OSI Approved :: MIT License
Classifier: Operating System :: OS Independent
Requires-Python: >=3.6
License-File: LICENSE.txt
Requires-Dist: regex
